geoaiagent/__init__.py
geoaiagent/__main__.py
geoaiagent/geoaiagent.py
geoaiagent-0.4.17.dist-info/METADATA
geoaiagent-0.4.17.dist-info/WHEEL
geoaiagent-0.4.17.dist-info/entry_points.txt
geoaiagent-0.4.17.dist-info/RECORD
