Metadata-Version: 2.4
Name: geoaiagent
Version: 0.4.17
Summary: Add your description here
Requires-Python: >=3.13
Requires-Dist: mcp
Requires-Dist: openpyxl
Requires-Dist: pandas
Requires-Dist: pathlib
Requires-Dist: scikit-learn
Requires-Dist: xgboost
